{"a":[{"testBools":[true,false],"testInts":[995193,1001854],"testUints":[1017570,1006482],"testDoubles":[987461,987802],"testStrings":["9\\uazl5OKwMXCVhbBfj3S\b\beF9of\tG2w\\0sVqsSD\\\r\td","HT\nbOAvN\rQEvlA\"H3\"RL\"dWV\re\b6M2YVxzpkJvSNd2"]}],"b":[{"testBools":[false,false],"testInts":[1010997,995032],"testUints":[987164,999452],"testDoubles":[1000429,1004623],"testStrings":["luSC\n2v\bTW3zVqjjMdSreui\n7f\rijE9Wx7h\\gcJGc\rgvvUjfBT","6aitrJdUofm\\wJ\r1R4BCo\bU8Nc7sj\rW\nl1ZikGDh"]}],"c":[{"testBools":[false,true,false],"testInts":[1003364,986546,994077],"testUints":[988492,1008722,996677],"testDoubles":[1020231,1003093,998349],"testStrings":["tTCja\\X4CG8\"R2y9ouIjvabA47A5OnlypbXUE7W5YvSG","hp\tu1es\rPs7L7ImMO\bb\tgxDvrsdFCqu\"MZCnWV","gZFsgwllj\\G\\5Q8V\\\rvQF5oP\niSL5GUuIRQbBQslwCzaBR"]}],"d":[{"testBools":[false,false],"testInts":[996637,1005194],"testUints":[1007670,999468],"testDoubles":[1009149,992907],"testStrings":["wNrEuL3\"H\rdzYhm5ZlD6Jl\bu\nAJM7RQnnmJ1jxJZ","k896tthuNxTkLSd5AaFOo\r\butJb8H3HGP5\nJMvo876"]}],"e":[{"testBools":[false,true],"testInts":[1007226,1001191],"testUints":[1009749,992565],"testDoubles":[980114,1002691],"testStrings":["AokVnZA\r43jyiryZB8egn57wT02lc3k2rTZ\"\"vNt25tu","ccOuzbZ7BJE7ALh\nQay8\t\\JhPY\\qMmLB\ntmATGHa"]}],"f":[{"testBools":[false,false],"testInts":[992607,997703],"testUints":[1003164,1012666],"testDoubles":[985600,991577],"testStrings":["v\bhwc4hW49XJ\n7DCVy1Fm7oid\bc87MxrB\bIzE\trWZJ7h\"7Xa0H","BoJcu5k3nNAvNZS9xrHjVX\"VP\t\r\bakAPUE\nGx\\nxTsW2"]}],"g":[{"testBools":[],"testInts":[],"testUints":[],"testDoubles":[],"testStrings":[]}],"h":[{"testBools":[false],"testInts":[1008312],"testUints":[1002278],"testDoubles":[994277],"testStrings":["\nL4B6eldC\"xE0trkuf\"\\\"j\\K\bOn\nHimRGgg1UL02z\n\rM"]}],"i":[{"testBools":[false,true,false],"testInts":[1006540,999215,995615],"testUints":[1005535,1005169,986874],"testDoubles":[998633,991055,996156],"testStrings":["Wg\bCXLx1W\"PhtTtmH32MUhKGLuEkmc4C7Gf\\Va7zLLX1","3NKao3RvcNC\t\n\r\rcQHf\nhH\\Ucv6Q1\tTOvD\"J6aK3UaWFLl","QBZ0\tLzzVWt43TyqS3vmcMjszob\nJTK5H32Xtqj3I0"]}],"j":[{"testBools":[false],"testInts":[994258],"testUints":[982397],"testDoubles":[1018010],"testStrings":["mEjQgdJ6KoFmf26fl\"RNejsXj\"ApGxZiltu\nMN1TSEyi"]}],"k":[{"testBools":[true,false],"testInts":[1008260,991214],"testUints":[1011163,983477],"testDoubles":[993747,1007114],"testStrings":["\nXHlVdQa\nE4W5\bmCdwUU59WIEMIz\tyP\bO8\tppugvzFr5","bpilDdM8XviLAbjoGcz4gF\t\nHtZxJpa\tv1t\neQQpb4"]}],"l":[{"testBools":[true],"testInts":[1016650],"testUints":[1006182],"testDoubles":[1011244],"testStrings":["\"JA6D\nCsMsSelY3IKGQKG5wPLUQNzI2\nUP"]}],"m":[{"testBools":[false,true],"testInts":[994353,1013092],"testUints":[1012478,1000451],"testDoubles":[1015447,1006756],"testStrings":["QBY8K1tMaY4bhXD\rNj\rSI6fYj5fNJhTjjMcWCiKT","LY0iL\rZAK\trPLIvva8np\rBrhmeXHPYZQVCpxjmSkxH3N2Z"]}],"n":[{"testBools":[],"testInts":[],"testUints":[],"testDoubles":[],"testStrings":[]}],"o":[{"testBools":[true,false],"testInts":[1013352,994041],"testUints":[998654,998225],"testDoubles":[1006117,1005856],"testStrings":["ZFqUlAQzUDxKJ9cWuIkOiUW9U\tl8\n5jJ\"WcHVk7GDu","OFLECiXFKkr6wzsRHRuOPMxaQ7Vb\np99\rjCNWk2wRYl1"]}],"p":[{"testBools":[false],"testInts":[992527],"testUints":[1017403],"testDoubles":[994541],"testStrings":["6g0erK9Z\rfF\\kBWYGthF2m1wsW5tPPJ\be0t1ZQ\tMT8Ry0O"]}],"q":[{"testBools":[false],"testInts":[992149],"testUints":[989593],"testDoubles":[1000102],"testStrings":["2j4uf\tU4gpv18S6I\\uimzRX\\\t\nvfhMw5TamkVZTke0Zl"]}],"r":[{"testBools":[true],"testInts":[988466],"testUints":[1012982],"testDoubles":[998529],"testStrings":["61Ci5\"70tHSWNxuDsMu8Ho\\80P1D\\1NQGvuK0\r1\tlxXj7okz1L0d"]}],"s":[{"testBools":[false],"testInts":[1012105],"testUints":[989271],"testDoubles":[1007886],"testStrings":["Ro7XtioA\nsEaR9Ipj\rfAsu\\tRL8IqexsdkQci2qD"]}],"t":[{"testBools":[false],"testInts":[988533],"testUints":[1001182],"testDoubles":[997908],"testStrings":["cN4er\\BCKz\\AehsHDi\nf\tN\b\"T5a8qtCskUG\\SM0LRGlp"]}],"u":[{"testBools":[true,true],"testInts":[1010553,995183],"testUints":[999300,1012975],"testDoubles":[1000857,1003063],"testStrings":["j\rNZoeadgjl90BHe\bY0LsCDi1yZwzBATFABtqVZhH6eT\nb","g\ndF6ZIuiPOCeJ3\\2PHZbSBBfRp\t8ZPgA\bf4OrDLIHjvg7"]}],"v":[{"testBools":[true],"testInts":[997786],"testUints":[992106],"testDoubles":[1001164],"testStrings":["gVmt0eiUcKQ\bUdKi2DKpON\rI\"\"Eo1V\"9HUGiO9Xd698c3KW\nOO"]}],"w":[{"testBools":[true],"testInts":[995998],"testUints":[998028],"testDoubles":[1001746],"testStrings":["tMKiC6yOpE\nSdVwrmF4dYxCh06YhpqdKVxA3d\bF\\7GfNI9jvDW"]}],"x":[{"testBools":[false,true,false],"testInts":[976427,1002756,1015189],"testUints":[1016013,987355,992124],"testDoubles":[989491,1005915,998082],"testStrings":["v0b\n\rAFcsuP8C\\AB\rIq4O\nbTI\noMg\bX6pO2l4OVOALKxkiLv","Ubunhy\tgiaXB\\uh4ok7ZgA\nZ4mY\"kP\"y\b3Pc\thfLnxFSuG\"z","Bx\nNRvThtvY0lRrnGPB\nHe\techWilPekWRXmrArM"]}],"y":[{"testBools":[false,true,true,true],"testInts":[1006460,998037,1006453,1002950],"testUints":[999948,1007421,998695,997984],"testDoubles":[1000444,978547,989163,987829],"testStrings":["h0ZJDHqaCUibQ7oyuJvenq3Av3dN\\Opj\rDU51DZH\ng26dJ","BB8ELTOa68AUpCThO8\"NSxpOC4eTAV\nlONs7","snuboyWym7XD8ieLRjbBAf1tWM8IyJyP65\tmVxvL","A5315z8\rtce6TQVTSBalRnMaRXcJPUgD2kE4F\tnTE\r6y"]}],"z":[{"testBools":[true,false,true],"testInts":[1014547,1005854,1006311],"testUints":[999815,991180,997692],"testDoubles":[1003965,997077,998841],"testStrings":["bFU9pj\\W6u\n5tEY\tVszMCX3c\\\\2aupytpLUHECOte4Jlx\b","pdeKmR8waIn8QrhuF\\Ew0WCKdoL44vbo359b51Umfi2i3uB9","ECbNrWC2KlVpv8\nGVWz\\JKg\b22aw\"aKe\nCjmKkCs"]}]}